README.txt
setup.py
collective/__init__.py
collective.jqueryVisualize.egg-info/PKG-INFO
collective.jqueryVisualize.egg-info/SOURCES.txt
collective.jqueryVisualize.egg-info/dependency_links.txt
collective.jqueryVisualize.egg-info/entry_points.txt
collective.jqueryVisualize.egg-info/namespace_packages.txt
collective.jqueryVisualize.egg-info/not-zip-safe
collective.jqueryVisualize.egg-info/requires.txt
collective.jqueryVisualize.egg-info/top_level.txt
collective/jqueryVisualize/__init__.py
collective/jqueryVisualize/configure.zcml
collective/jqueryVisualize/profiles/default/cssregistry.xml
collective/jqueryVisualize/profiles/default/jsregistry.xml
collective/jqueryVisualize/profiles/default/metadata.xml
collective/jqueryVisualize/resources/__init__.py
collective/jqueryVisualize/resources/css/visualize-dark.css
collective/jqueryVisualize/resources/css/visualize-light.css
collective/jqueryVisualize/resources/css/visualize.css
collective/jqueryVisualize/resources/images/chartbg-vanilla.png
collective/jqueryVisualize/resources/images/chartbg.png
collective/jqueryVisualize/resources/js/example.js
collective/jqueryVisualize/resources/js/excanvas.js
collective/jqueryVisualize/resources/js/visualize.jQuery.js
docs/HISTORY.txt