Metadata-Version: 1.0
Name: collective.jqueryVisualize
Version: 1.0
Summary: Provides the jQuery Visualize library to Plone
Home-page: http://svn.plone.org/svn/collective/
Author: UNKNOWN
Author-email: UNKNOWN
License: GPL
Platform: UNKNOWN
Classifier: Framework :: Plone
Classifier: Programming Language :: Python
